python_da.so
python_da-0.0.6.dist-info/DESCRIPTION.rst
python_da-0.0.6.dist-info/METADATA
python_da-0.0.6.dist-info/RECORD
python_da-0.0.6.dist-info/WHEEL
python_da-0.0.6.dist-info/metadata.json
python_da-0.0.6.dist-info/top_level.txt
